qubovert/__init__.py
qubovert/__main__.py
qubovert/_pcbo.py
qubovert/_pcso.py
qubovert/_pubo.py
qubovert/_puso.py
qubovert/_qubo.py
qubovert/_quso.py
qubovert/_version.py
qubovert/problems/__init__.py
qubovert/problems/__main__.py
qubovert/problems/_problem_parentclass.py
qubovert/problems/benchmarking/__init__.py
qubovert/problems/benchmarking/__main__.py
qubovert/problems/benchmarking/_alternating_sectors_chain.py
qubovert/problems/np/__init__.py
qubovert/problems/np/__main__.py
qubovert/problems/np/bilp/__init__.py
qubovert/problems/np/bilp/__main__.py
qubovert/problems/np/bilp/_bilp.py
qubovert/problems/np/coloring/__init__.py
qubovert/problems/np/coloring/__main__.py
qubovert/problems/np/coloring/_job_sequencing.py
qubovert/problems/np/covering/__init__.py
qubovert/problems/np/covering/__main__.py
qubovert/problems/np/covering/_set_cover.py
qubovert/problems/np/covering/_vertex_cover.py
qubovert/problems/np/cycles/__init__.py
qubovert/problems/np/cycles/__main__.py
qubovert/problems/np/packing/__init__.py
qubovert/problems/np/packing/__main__.py
qubovert/problems/np/partitioning/__init__.py
qubovert/problems/np/partitioning/__main__.py
qubovert/problems/np/partitioning/_graph_partitioning.py
qubovert/problems/np/partitioning/_number_partitioning.py
qubovert/problems/np/tree/__init__.py
qubovert/problems/np/tree/__main__.py
qubovert/sat/__init__.py
qubovert/sat/__main__.py
qubovert/sat/_satisfiability.py
qubovert/sim/__init__.py
qubovert/sim/__main__.py
qubovert/sim/_anneal.py
qubovert/sim/_anneal_results.py
qubovert/sim/_anneal_temperature_range.py
qubovert/sim/_canneal.c
qubovert/sim/_canneal.cpython-38-darwin.so
qubovert/sim/src/anneal_puso.c
qubovert/sim/src/anneal_puso.h
qubovert/sim/src/anneal_quso.c
qubovert/sim/src/anneal_quso.h
qubovert/sim/src/pcg_basic.c
qubovert/sim/src/pcg_basic.h
qubovert/sim/src/random.c
qubovert/sim/src/random.h
qubovert/utils/__init__.py
qubovert/utils/__main__.py
qubovert/utils/_approximate_extrema.py
qubovert-1.2.5.dist-info/LICENSE
qubovert-1.2.5.dist-info/METADATA
qubovert-1.2.5.dist-info/WHEEL
qubovert-1.2.5.dist-info/top_level.txt
qubovert-1.2.5.dist-info/RECORD
