Metadata-Version: 2.1
Name: qubovert
Version: 1.2.5
Summary: A package for formulating, simulating, and solving problems in boolean and spin form
Home-page: https://github.com/jtiosue/qubovert
Author: Joseph T. Iosue
Author-email: jtiosue@gmail.com
License: Apache Software License 2.0
Project-URL: Source, https://github.com/jtiosue/qubovert
Project-URL: Docs, https://qubovert.readthedocs.io
Platform: UNKNOWN
Classifier: Programming Language :: Python :: 3
Classifier: License :: OSI Approved :: Apache Software License
Classifier: Operating System :: OS Independent
Requires-Dist: numpy
